mics/MBAR.py
mics/MICS.py
mics/__init__.py
mics/mixtures.py
mics/samples.py
mics/utils.py
mics-0.2.0.dist-info/DESCRIPTION.rst
mics-0.2.0.dist-info/METADATA
mics-0.2.0.dist-info/RECORD
mics-0.2.0.dist-info/WHEEL
mics-0.2.0.dist-info/metadata.json
mics-0.2.0.dist-info/top_level.txt
