Metadata-Version: 2.0
Name: mics
Version: 0.2.0
Summary: Mixtures of Independently Collected Samples
Home-page: https://github.com/craabreu/mics
Author: Charlles R. A. Abreu
Author-email: abreu@eq.ufrj.br
License: MIT license
Platform: UNKNOWN
Classifier: Development Status :: 5 - Production/Stable
Classifier: Intended Audience :: Developers
Classifier: License :: OSI Approved :: MIT License
Classifier: Operating System :: Unix
Classifier: Operating System :: POSIX
Classifier: Operating System :: Microsoft :: Windows
Classifier: Programming Language :: Python
Classifier: Programming Language :: Python :: 2.7
Classifier: Programming Language :: Python :: 3
Classifier: Programming Language :: Python :: 3.5
Classifier: Programming Language :: Python :: 3.6
Classifier: Topic :: Utilities
Requires-Dist: numpy (>=1.13.0)
Requires-Dist: scipy (>=0.19.1)
Requires-Dist: sympy (>=1.1.1)
Requires-Dist: pandas (>=0.21.0)
Requires-Dist: six (>=1.10.0)
Requires-Dist: pymbar (>=3.0.3)
